sc3D/__init__.py
sc3D/sc3D.py
sc3D/transformations.py
sc3D/_tests/__init__.py
sc3D/_tests/test_sc3D.py
sc_3d-2.0.0.dist-info/licenses/LICENSE
sc_3d-2.0.0.dist-info/METADATA
sc_3d-2.0.0.dist-info/WHEEL
sc_3d-2.0.0.dist-info/top_level.txt
sc_3d-2.0.0.dist-info/RECORD
