Metadata-Version: 2.4
Name: sc-3D
Version: 2.0.0
Summary: Array alignment and 3D differential expression for 3D sc omics
Home-page: https://github.com/GuignardLab/sc3D
Author: Leo Guignard
Author-email: leo.guignard@univ-amu.fr
License: MIT
Project-URL: Bug Tracker, https://github.com/GuignardLab/sc3D/issues
Project-URL: Documentation, https://github.com/GuignardLab/sc3D#README.md
Project-URL: Source Code, https://github.com/GuignardLab/sc3D
Project-URL: User Support, https://github.com/GuignardLab/sc3D/issues
Project-URL: Twitter, https://twitter.com/guignardlab
Classifier: Development Status :: 4 - Beta
Classifier: Intended Audience :: Developers
Classifier: Topic :: Software Development :: Testing
Classifier: Programming Language :: Python
Classifier: Programming Language :: Python :: 3
Classifier: Programming Language :: Python :: 3.8
Classifier: Programming Language :: Python :: 3.9
Classifier: Programming Language :: Python :: 3.10
Classifier: Operating System :: OS Independent
Classifier: License :: OSI Approved :: MIT License
Requires-Python: >=3.8
License-File: LICENSE
Requires-Dist: scipy
Requires-Dist: numpy
Requires-Dist: matplotlib
Requires-Dist: pandas
Requires-Dist: seaborn
Requires-Dist: scikit-learn
Requires-Dist: anndata
Provides-Extra: testing
Requires-Dist: tox; extra == "testing"
Requires-Dist: pytest; extra == "testing"
Requires-Dist: pytest-cov; extra == "testing"
Dynamic: license-file
